tinq/__init__.py
tinq/api_client.py
tinq/api_response.py
tinq/configuration.py
tinq/exceptions.py
tinq/py.typed
tinq/rest.py
tinq/api/__init__.py
tinq/api/assistant.py
tinq/api/classifiers.py
tinq/api/plagiarism_checker.py
tinq/api/projects.py
tinq/api/scraper.py
tinq/api/tools.py
tinq/api/workflows.py
tinq/models/__init__.py
tinq-0.2.1.dist-info/LICENSE.txt
tinq-0.2.1.dist-info/METADATA
tinq-0.2.1.dist-info/WHEEL
tinq-0.2.1.dist-info/top_level.txt
tinq-0.2.1.dist-info/RECORD
