Metadata-Version: 2.1
Name: tinq
Version: 0.2.1
Summary: Tinq AI V2
Home-page: https://pypi.org/project/tinq/appDescription&#x3D;Official Tinq.ai python SDKprojectName&#x3D;tinq
Author: Boulama
Author-email: Boulama <boulama@tinq.ai>
Project-URL: Homepage, https://github.com/tinq-ai/tinq-python
Project-URL: Bug Tracker, https://github.com/tinq-ai/tinq-python/issues
Classifier: Development Status :: 2 - Pre-Alpha
Classifier: Programming Language :: Python :: 3
Classifier: License :: OSI Approved :: MIT License
Classifier: Operating System :: OS Independent
Requires-Python: >=3.7
License-File: LICENSE.txt
Requires-Dist: urllib3 <3.0.0,>=1.25.3
Requires-Dist: python-dateutil >=2.8.2
Requires-Dist: pydantic >=2
Requires-Dist: typing-extensions >=4.7.1
